PirxcyPackage/__init__.py
PirxcyPackage-20.0.3.dist-info/METADATA
PirxcyPackage-20.0.3.dist-info/WHEEL
PirxcyPackage-20.0.3.dist-info/top_level.txt
PirxcyPackage-20.0.3.dist-info/RECORD
