Metadata-Version: 2.1
Name: PirxcyPackage
Version: 20.0.3
Summary: PirxcyBot in a PyPi package form to easily be ran on repl. Or in a simple py file
Home-page: https://github.com/PirxcyFinal/PirxcyBotFiles
Author: Pirxcy
License: UNKNOWN
Platform: UNKNOWN
Classifier: Programming Language :: Python :: 3
Classifier: License :: OSI Approved :: MIT License
Classifier: Operating System :: OS Independent
Requires-Dist: crayons
Requires-Dist: fortnitepy
Requires-Dist: psutil
Requires-Dist: pypresence
Requires-Dist: BenBotAsync
Requires-Dist: FortniteAPIAsync
Requires-Dist: colorama
Requires-Dist: uvloop
Requires-Dist: sanic
Requires-Dist: time
Requires-Dist: aiohttp
